seqqueue/__init__.py
seqqueue/seqthreadqueue.py
seqqueue-0.4.dist-info/LICENSE.txt
seqqueue-0.4.dist-info/METADATA
seqqueue-0.4.dist-info/WHEEL
seqqueue-0.4.dist-info/top_level.txt
seqqueue-0.4.dist-info/RECORD
