Metadata-Version: 2.1
Name: seqqueue
Version: 0.4
Summary: Collections of queues to handle sequentially tagged objects
Home-page: https://github.com/highvight/seqqueue
Author: highvight
Author-email: adriankrueger@gmail.com
License: MIT
Platform: any
Classifier: Development Status :: 4 - Beta
Classifier: Programming Language :: Python
License-File: LICENSE.txt
Requires-Dist: importlib-metadata
Provides-Extra: testing
Requires-Dist: setuptools ; extra == 'testing'
Requires-Dist: pytest ; extra == 'testing'
Requires-Dist: pytest-benchmark ; extra == 'testing'
